entoli/__init__.py
entoli/http_client.py
entoli/prelude.py
entoli/process.py
entoli/control/__init__.py
entoli/control/concurrent.py
entoli/data/__init__.py
entoli/data/alternative.py
entoli/data/applicative.py
entoli/data/foldable.py
entoli/data/functor.py
entoli/data/maybe.py
entoli/data/monad.py
entoli/data/monad_plus.py
entoli/data/monoid.py
entoli/data/ord.py
entoli/data/semigroup.py
entoli/data/seq.py
entoli/data/tree.py
entoli/parsec/__init__.py
entoli/parsec/char.py
entoli/parsec/combinator.py
entoli/parsec/prim.py
entoli/system/__init__.py
entoli/system/io.py
entoli/text/__init__.py
entoli/text/show.py
entoli-0.1.5.dist-info/LICENSE
entoli-0.1.5.dist-info/METADATA
entoli-0.1.5.dist-info/WHEEL
entoli-0.1.5.dist-info/top_level.txt
entoli-0.1.5.dist-info/RECORD
