Metadata-Version: 2.1
Name: entoli
Version: 0.1.5
Summary: A Python functional programming library
Home-page: https://github.com/cwahn/entoli
Author: Chanwoo Ahn
Author-email: cwahn0904@gmail.com
Classifier: Programming Language :: Python :: 3
Classifier: License :: OSI Approved :: MIT License
Classifier: Operating System :: OS Independent
Requires-Python: >=3.12
License-File: LICENSE
Provides-Extra: dev
Requires-Dist: attrs (==23.2.0) ; extra == 'dev'
Requires-Dist: certifi (==2024.2.2) ; extra == 'dev'
Requires-Dist: charset-normalizer (==3.3.2) ; extra == 'dev'
Requires-Dist: distlib (==0.3.8) ; extra == 'dev'
Requires-Dist: docutils (==0.21.2) ; extra == 'dev'
Requires-Dist: filelock (==3.14.0) ; extra == 'dev'
Requires-Dist: idna (==3.7) ; extra == 'dev'
Requires-Dist: importlib-metadata (==7.1.0) ; extra == 'dev'
Requires-Dist: iniconfig (==2.0.0) ; extra == 'dev'
Requires-Dist: jaraco.classes (==3.4.0) ; extra == 'dev'
Requires-Dist: jaraco.context (==5.3.0) ; extra == 'dev'
Requires-Dist: jaraco.functools (==4.0.1) ; extra == 'dev'
Requires-Dist: keyring (==25.2.1) ; extra == 'dev'
Requires-Dist: markdown-it-py (==3.0.0) ; extra == 'dev'
Requires-Dist: mdurl (==0.1.2) ; extra == 'dev'
Requires-Dist: more-itertools (==10.2.0) ; extra == 'dev'
Requires-Dist: nh3 (==0.2.17) ; extra == 'dev'
Requires-Dist: packaging (==24.0) ; extra == 'dev'
Requires-Dist: pkginfo (==1.10.0) ; extra == 'dev'
Requires-Dist: platformdirs (==4.2.2) ; extra == 'dev'
Requires-Dist: pluggy (==0.13.1) ; extra == 'dev'
Requires-Dist: py (==1.11.0) ; extra == 'dev'
Requires-Dist: Pygments (==2.18.0) ; extra == 'dev'
Requires-Dist: pytest (==6.2.4) ; extra == 'dev'
Requires-Dist: readme-renderer (==43.0) ; extra == 'dev'
Requires-Dist: requests (==2.32.2) ; extra == 'dev'
Requires-Dist: requests-toolbelt (==1.0.0) ; extra == 'dev'
Requires-Dist: rfc3986 (==2.0.0) ; extra == 'dev'
Requires-Dist: rich (==13.7.1) ; extra == 'dev'
Requires-Dist: ruff (==0.3.5) ; extra == 'dev'
Requires-Dist: setuptools (==70.0.0) ; extra == 'dev'
Requires-Dist: toml (==0.10.2) ; extra == 'dev'
Requires-Dist: twine (==5.1.0) ; extra == 'dev'
Requires-Dist: urllib3 (==2.2.1) ; extra == 'dev'
Requires-Dist: virtualenv (==20.26.2) ; extra == 'dev'
Requires-Dist: wheel (==0.33.6) ; extra == 'dev'
Requires-Dist: zipp (==3.19.0) ; extra == 'dev'
